versum/__init__.py
versum/crypt/__init__.py
versum/crypt/passwd/__init__.py
versum/crypt/passwd/exceptions.py
versum/crypt/passwd/pw_manager.py
versum/exceptions/__init__.py
versum-0.1.2.dist-info/METADATA
versum-0.1.2.dist-info/WHEEL
versum-0.1.2.dist-info/entry_points.txt
versum-0.1.2.dist-info/RECORD
